walacor_data_tracker/__init__.py
walacor_data_tracker/adapters/__init__.py
walacor_data_tracker/adapters/base.py
walacor_data_tracker/adapters/pandas_adapter.py
walacor_data_tracker/core/__init__.py
walacor_data_tracker/core/events.py
walacor_data_tracker/core/history.py
walacor_data_tracker/core/snapshot.py
walacor_data_tracker/core/tracker.py
walacor_data_tracker/core/utils.py
walacor_data_tracker/writers/__init__.py
walacor_data_tracker/writers/console/__init__.py
walacor_data_tracker/writers/console/console_writer.py
walacor_data_tracker/writers/walacor/__init__.py
walacor_data_tracker/writers/walacor/_json.py
walacor_data_tracker/writers/walacor/catalog.py
walacor_data_tracker/writers/walacor/schema_builder.py
walacor_data_tracker/writers/walacor/walacor_client.py
walacor_data_tracker/writers/walacor/walacor_writer.py
walacor_data_tracker-0.0.5.dist-info/licenses/LICENSE
walacor_data_tracker-0.0.5.dist-info/METADATA
walacor_data_tracker-0.0.5.dist-info/WHEEL
walacor_data_tracker-0.0.5.dist-info/top_level.txt
walacor_data_tracker-0.0.5.dist-info/RECORD
